src/__init__.py
src/analytical_flux.py
src/base_functions.py
src/models.py
src/superconductor_losses.py
src/transformer_fem_model.py
src/two_winding_model.py
trafocalc-2022.1.1.dist-info/LICENSE
trafocalc-2022.1.1.dist-info/WHEEL
trafocalc-2022.1.1.dist-info/METADATA
trafocalc-2022.1.1.dist-info/RECORD
